[{"model": "app.selfemployedactivities", "pk": 1, "fields": {"self_employed": 1, "activity": 4, "importance": false}}, {"model": "app.selfemployedactivities", "pk": 2, "fields": {"self_employed": 1, "activity": 5, "importance": false}}, {"model": "app.selfemployedactivities", "pk": 3, "fields": {"self_employed": 3, "activity": 4, "importance": false}}, {"model": "app.selfemployedactivities", "pk": 4, "fields": {"self_employed": 3, "activity": 1, "importance": false}}, {"model": "app.selfemployedactivities", "pk": 5, "fields": {"self_employed": 7, "activity": 2, "importance": false}}]